mermaid_parser/__init__.py
mermaid_parser/lib/mermaid_syntax_parser.cjs
mermaid_parser/py.typed
mermaid_parser/validator.py
mermaid_syntax_parser-0.2.2.dist-info/METADATA
mermaid_syntax_parser-0.2.2.dist-info/WHEEL
mermaid_syntax_parser-0.2.2.dist-info/RECORD
