Metadata-Version: 2.1
Name: mermaid-syntax-parser
Version: 0.2.2
Summary: 
Author: Roy M Mezan
Author-email: 88roy88@gmail.com
Requires-Python: >=3.11,<4.0
Classifier: Programming Language :: Python :: 3
Classifier: Programming Language :: Python :: 3.11
Classifier: Programming Language :: Python :: 3.12
Requires-Dist: pythonmonkey (>=1.1.0,<2.0.0)
